pypermission/__init__.py
pypermission/db.py
pypermission/example/app.py
pypermission/example/models.py
pypermission/example/service/group.py
pypermission/example/service/user.py
pypermission/exc.py
pypermission/models.py
pypermission/py.typed
pypermission/service/__init__.py
pypermission/service/role.py
pypermission/service/subject.py
pypermission/util/__init__.py
pypermission/util/exception_handling.py
pypermission/util/plot.py
pypermission/util/role.py
pypermission-0.3.0.dist-info/WHEEL
pypermission-0.3.0.dist-info/METADATA
pypermission-0.3.0.dist-info/RECORD
