Metadata-Version: 2.4
Name: PyPermission
Version: 0.3.0
Summary: The python RBAC authorization library for projects where SQLAlchemy is a valid option.
Author: Jendrik A. Potyka, Fabian A. Preiss
Author-email: Jendrik A. Potyka <jpotyka@digon.io>, Fabian A. Preiss <fpreiss@digon.io>
License-Expression: LGPL-3.0-only
Classifier: Development Status :: 4 - Beta
Classifier: Intended Audience :: Developers
Classifier: License :: OSI Approved :: GNU Lesser General Public License v3 (LGPLv3)
Classifier: Programming Language :: Python :: 3.13
Classifier: Programming Language :: Python :: 3.14
Classifier: Programming Language :: Python :: Implementation :: CPython
Classifier: Topic :: Software Development :: Libraries
Classifier: Topic :: Security
Classifier: Operating System :: OS Independent
Classifier: Typing :: Typed
Requires-Dist: sqlalchemy>=2.0.43
Requires-Dist: psycopg>=3.2.10 ; extra == 'postgres'
Requires-Dist: networkx>=3.5 ; extra == 'util'
Requires-Dist: plotly>=6.3.1 ; extra == 'util'
Maintainer: Jendrik A. Potyka, Fabian A. Preiss
Maintainer-email: Jendrik A. Potyka <jpotyka@digon.io>, Fabian A. Preiss <fpreiss@digon.io>
Requires-Python: >=3.13
Project-URL: Changelog, https://gitlab.com/DigonIO/pypermission/-/blob/main/CHANGELOG.md
Project-URL: Documentation, https://pypermission.digon.io
Project-URL: Issues, https://gitlab.com/DigonIO/pypermission/-/issues
Project-URL: Repository, https://gitlab.com/DigonIO/pypermission
Provides-Extra: postgres
Provides-Extra: util
